[
    {
        "id": 1,
        "fullName": "Camisetas Personalizadas",
        "price": 18000,
        "productLine": "Linea fashion",
        "activity": "Eventos",
        "subActivity": [
            "Campañas Publicitarias",
            "Campañas Políticas",
            "Eventos Corporativos"
        ],
        "technique": [
            "Full color sublimación",
            "Full color sublimación"
        ],
        "material": [
            "Algodón",
            "Poliester"
        ],
        "image": "fashion.png"
    },
    {
        "id": 2,
        "fullname": "asdasd",
        "price": 1,
        "product_line": "Linea industrial",
        "activity": "Fashion",
        "subactivity": [
            "campañas-politicas",
            "eventos-coporporativos"
        ],
        "service": "Vinilo textil 1 color",
        "tela": [
            "algodon",
            "poliester"
        ],
        "image": "chompa_even.png"
    },
    {
        "id": 3,
        "fullname": "asdas",
        "price": 21,
        "productLine": "Linea medica",
        "service": "Empresariales",
        "subactivity": [
            "campañas-publicitarias",
            "eventos-coporporativos"
        ],
        "technique": [
            "full-color-sublimacion",
            "vinilo-textil-1-color"
        ],
        "material": [
            "algodon",
            "poliester"
        ],
        "image": "chompa_even.png"
    }
]